nobinobi_observation/__init__.py
nobinobi_observation/admin.py
nobinobi_observation/apps.py
nobinobi_observation/forms.py
nobinobi_observation/menus.py
nobinobi_observation/models.py
nobinobi_observation/serializers.py
nobinobi_observation/signals.py
nobinobi_observation/urls.py
nobinobi_observation/utils.py
nobinobi_observation/views.py
nobinobi_observation/locale/en/LC_MESSAGES/django.po
nobinobi_observation/locale/fr/LC_MESSAGES/django.mo
nobinobi_observation/locale/fr/LC_MESSAGES/django.po
nobinobi_observation/migrations/0001_initial.py
nobinobi_observation/migrations/0002_auto_20190611_1051.py
nobinobi_observation/migrations/0003_auto_20200219_1049.py
nobinobi_observation/migrations/__init__.py
nobinobi_observation/static/css/nobinobi_observation.css
nobinobi_observation/static/img/.gitignore
nobinobi_observation/static/js/nobinobi_observation.js
nobinobi_observation/templates/nobinobi_observation/observation_choice.html
nobinobi_observation/templates/nobinobi_observation/observation_confirm_delete.html
nobinobi_observation/templates/nobinobi_observation/observation_detail.html
nobinobi_observation/templates/nobinobi_observation/observation_detail_list.html
nobinobi_observation/templates/nobinobi_observation/observation_form.html
nobinobi_observation/templates/nobinobi_observation/observation_list.html
nobinobi_observation/templates/nobinobi_observation/observation_update.html
nobinobi_observation/test_utils/__init__.py
nobinobi_observation/test_utils/test_app/__init__.py
nobinobi_observation/test_utils/test_app/admin.py
nobinobi_observation/test_utils/test_app/apps.py
nobinobi_observation/test_utils/test_app/models.py
nobinobi_observation/test_utils/test_app/migrations/__init__.py
nobinobi_observation-0.1.4.dist-info/AUTHORS.rst
nobinobi_observation-0.1.4.dist-info/LICENSE
nobinobi_observation-0.1.4.dist-info/METADATA
nobinobi_observation-0.1.4.dist-info/WHEEL
nobinobi_observation-0.1.4.dist-info/top_level.txt
nobinobi_observation-0.1.4.dist-info/RECORD
