Metadata-Version: 2.1
Name: nobinobi-observation
Version: 0.1.4
Summary: Application Observation for Nobinobi
Home-page: https://github.com/prolibre-ch/nobinobi-observation
Author: Florian Alu
Author-email: alu@prolibre.com
License: UNKNOWN
Keywords: nobinobi-observation
Platform: UNKNOWN
Classifier: Development Status :: 4 - Beta
Classifier: Framework :: Django :: 3.2
Classifier: Intended Audience :: Developers
Classifier: License :: OSI Approved :: GNU Affero General Public License v3 or later (AGPLv3+)
Classifier: Natural Language :: English
Classifier: Programming Language :: Python :: 3
Classifier: Programming Language :: Python :: 3.6
Classifier: Programming Language :: Python :: 3.7
Classifier: Programming Language :: Python :: 3.8
Requires-Dist: nobinobi-child (==0.1.3.7)
